Metadata-Version: 1.2
Name: redash-tools
Version: 1.0.2
Summary: Tools to backup, batch update, template redash queries and dashboards
Home-page: http://github.com/pavlova-marina/redash-tools
Author: Marina Pavlova
Author-email: pavlova.marina.v@gmail.com
License: MIT
Download-URL: https://github.com/pavlova-marina/redash-tools/archive/refs/tags/v1.0.2.tar.gz
Keywords: redash
Platform: UNKNOWN
Classifier: Development Status :: 3 - Alpha
Classifier: Intended Audience :: Developers
Classifier: Topic :: Software Development :: Build Tools
Classifier: License :: OSI Approved :: MIT License
Classifier: Operating System :: OS Independent
Classifier: Programming Language :: Python :: 3
Classifier: Programming Language :: Python :: 3.4
Classifier: Programming Language :: Python :: 3.5
Classifier: Programming Language :: Python :: 3.6
Requires-Python: >=3.6
